cherab/solps/__init__.pxd
cherab/solps/__init__.py
cherab/solps/mesh_geometry.py
cherab/solps/plot.py
cherab/solps/solps_2d_functions.cpython-312-x86_64-linux-gnu.so
cherab/solps/solps_2d_functions.pxd
cherab/solps/solps_plasma.py
cherab/solps/b2/__init__.py
cherab/solps/b2/parse_b2_block_file.py
cherab/solps/eirene/__init__.py
cherab/solps/eirene/eirene.py
cherab/solps/eirene/parser/__init__.py
cherab/solps/eirene/parser/fort44.py
cherab/solps/eirene/parser/fort44_2013.py
cherab/solps/eirene/parser/fort44_post_2016.py
cherab/solps/eirene/parser/fort44_pre_2007.py
cherab/solps/eirene/parser/utility.py
cherab/solps/formats/__init__.py
cherab/solps/formats/balance.py
cherab/solps/formats/mdsplus.py
cherab/solps/formats/raw_simulation_files.py
cherab/solps/models/__init__.pxd
cherab/solps/models/__init__.py
cherab/solps/models/line_emitter.cpython-312-x86_64-linux-gnu.so
cherab/solps/models/line_emitter.pxd
cherab/solps/models/solps_emitter.py
cherab/solps/tests/__init__.py
cherab/solps/tests/test_mesh.py
cherab/solps/tests/test_simulation.py
cherab_solps-1.3.0.data/data/share/cherab/demos/solps/demos/aug_solps_from_files.py
cherab_solps-1.3.0.data/data/share/cherab/demos/solps/demos/generomak_raw_files_image_plasma.py
cherab_solps-1.3.0.data/data/share/cherab/demos/solps/demos/generomak_raw_files_plot_profiles.py
cherab_solps-1.3.0.data/data/share/cherab/demos/solps/demos/generomak_raw_files_solps_emitter.py
cherab_solps-1.3.0.data/data/share/cherab/demos/solps/demos/generomak_raw_files_solps_line_emitter.py
cherab_solps-1.3.0.data/data/share/cherab/demos/solps/demos/mastu_solps_from_mdsplus.py
cherab_solps-1.3.0.data/data/share/cherab/demos/solps/demos/solps_from_balance.py
cherab_solps-1.3.0.data/data/share/cherab/demos/solps/demos/data/raw/b2fgmtry
cherab_solps-1.3.0.data/data/share/cherab/demos/solps/demos/data/raw/b2fstate
cherab_solps-1.3.0.data/data/share/cherab/demos/solps/demos/data/raw/fort.44
cherab_solps-1.3.0.dist-info/METADATA
cherab_solps-1.3.0.dist-info/WHEEL
cherab_solps-1.3.0.dist-info/RECORD
cherab_solps-1.3.0.dist-info/licenses/LICENCE.txt
