Metadata-Version: 2.1
Name: cherab-solps
Version: 1.3.0
Summary: Cherab spectroscopy framework: SOLPS submodule
Home-page: https://github.com/cherab
License: European Union Public Licence
Classifier: Development Status :: 5 - Production/Stable
Classifier: Intended Audience :: Science/Research
Classifier: Intended Audience :: Education
Classifier: Intended Audience :: Developers
Classifier: Natural Language :: English
Classifier: Operating System :: POSIX :: Linux
Classifier: Programming Language :: Cython
Classifier: Programming Language :: Python :: 3
Classifier: Topic :: Scientific/Engineering :: Physics
Project-URL: Homepage, https://github.com/cherab
Project-URL: Documentation, https://www.cherab.info
Project-URL: Repository, https://github.com/cherab/solps
Project-URL: Issues, https://github.com/cherab/solps/issues
Requires-Python: >=3.7
Requires-Dist: raysect==0.8.1.*
Requires-Dist: cherab==1.5.*
Requires-Dist: matplotlib
Requires-Dist: scipy
